promptstorepy/ApiService.py
promptstorepy/KeycloakAuth.py
promptstorepy/LangChainCallbackHandler.py.bak
promptstorepy/PromptStore.py
promptstorepy/Tracing.py
promptstorepy/__init__.py
promptstorepy/utils.py
promptstorepy-0.1.2.dist-info/METADATA
promptstorepy-0.1.2.dist-info/WHEEL
promptstorepy-0.1.2.dist-info/RECORD
