Metadata-Version: 2.1
Name: promptstorepy
Version: 0.1.2
Summary: 
Author: Mark Moloney
Author-email: markmo@me.com
Requires-Python: >=3.11,<4.0
Classifier: Programming Language :: Python :: 3
Classifier: Programming Language :: Python :: 3.11
Classifier: Programming Language :: Python :: 3.12
Requires-Dist: asyncio (>=3.4.3,<4.0.0)
Requires-Dist: devtools (>=0.12.2,<0.13.0)
Requires-Dist: requests (>=2.32.2,<3.0.0)
